[{"status":0,"hits":2,"isIndestructible":false,"colorIndex":5},{"status":0,"hits":3,"isIndestructible":false,"colorIndex":5},{"status":0,"hits":1,"isIndestructible":false,"colorIndex":5},{"status":0,"hits":2,"isIndestructible":false,"colorIndex":3},{"status":0,"hits":1,"isIndestructible":false,"colorIndex":2},{"status":1,"hits":1,"isIndestructible":false,"colorIndex":0},{"status":1,"hits":1,"isIndestructible":false,"colorIndex":0},{"status":1,"hits":1,"isIndestructible":false,"colorIndex":0},{"status":1,"hits":1,"isIndestructible":false,"colorIndex":0},{"status":1,"hits":1,"isIndestructible":false,"colorIndex":0},{"status":1,"hits":1,"isIndestructible":false,"colorIndex":2},{"status":1,"hits":1,"isIndestructible":false,"colorIndex":2},{"status":1,"hits":1,"isIndestructible":false,"colorIndex":2},{"status":1,"hits":1,"isIndestructible":false,"colorIndex":2},{"status":1,"hits":1,"isIndestructible":false,"colorIndex":0},{"status":1,"hits":1,"isIndestructible":false,"colorIndex":1},{"status":1,"hits":1,"isIndestructible":false,"colorIndex":1},{"status":1,"hits":1,"isIndestructible":false,"colorIndex":1},{"status":1,"hits":1,"isIndestructible":false,"colorIndex":2},{"status":1,"hits":1,"isIndestructible":false,"colorIndex":0},{"status":1,"hits":1,"isIndestructible":false,"colorIndex":3},{"status":1,"hits":1,"isIndestructible":false,"colorIndex":3},{"status":1,"hits":1,"isIndestructible":false,"colorIndex":1},{"status":1,"hits":1,"isIndestructible":false,"colorIndex":2},{"status":1,"hits":1,"isIndestructible":false,"colorIndex":0},{"status":1,"hits":1,"isIndestructible":false,"colorIndex":4},{"status":1,"hits":1,"isIndestructible":false,"colorIndex":3},{"status":1,"hits":1,"isIndestructible":false,"colorIndex":1},{"status":1,"hits":1,"isIndestructible":false,"colorIndex":2},{"status":1,"hits":1,"isIndestructible":false,"colorIndex":0},{"status":1,"hits":1,"isIndestructible":false,"colorIndex":4},{"status":1,"hits":1,"isIndestructible":false,"colorIndex":3},{"status":1,"hits":1,"isIndestructible":false,"colorIndex":1},{"status":1,"hits":1,"isIndestructible":false,"colorIndex":2},{"status":1,"hits":1,"isIndestructible":false,"colorIndex":0},{"status":1,"hits":1,"isIndestructible":false,"colorIndex":4},{"status":1,"hits":1,"isIndestructible":false,"colorIndex":3},{"status":1,"hits":1,"isIndestructible":false,"colorIndex":1},{"status":1,"hits":1,"isIndestructible":false,"colorIndex":2},{"status":1,"hits":1,"isIndestructible":false,"colorIndex":0},{"status":1,"hits":1,"isIndestructible":false,"colorIndex":4},{"status":1,"hits":1,"isIndestructible":false,"colorIndex":3},{"status":1,"hits":1,"isIndestructible":false,"colorIndex":1},{"status":1,"hits":1,"isIndestructible":false,"colorIndex":2},{"status":1,"hits":1,"isIndestructible":false,"colorIndex":0},{"status":1,"hits":1,"isIndestructible":false,"colorIndex":4},{"status":1,"hits":1,"isIndestructible":false,"colorIndex":3},{"status":1,"hits":1,"isIndestructible":false,"colorIndex":1},{"status":1,"hits":1,"isIndestructible":false,"colorIndex":2},{"status":1,"hits":1,"isIndestructible":false,"colorIndex":0}]